form_schema_generator/__init__.py
form_schema_generator/apps.py
form_schema_generator/enum_meta.py
form_schema_generator/enums.py
form_schema_generator/generator.py
form_schema_generator/serializers.py
form_schema_generator/settings.py
form_schema_generator/urls.py
form_schema_generator/viewset.py
form_schema_generator/convertors/__init__.py
form_schema_generator/convertors/base.py
form_schema_generator/convertors/vue_formulator.py
form_schema_generator-1.15.dist-info/METADATA
form_schema_generator-1.15.dist-info/WHEEL
form_schema_generator-1.15.dist-info/top_level.txt
form_schema_generator-1.15.dist-info/RECORD
